appenlight/__init__.py
appenlight/fil.py
appenlight/forms.py
appenlight/predicates.py
appenlight/security.py
appenlight/subscribers.py
appenlight/validators.py
appenlight/celery/__init__.py
appenlight/celery/encoders.py
appenlight/celery/tasks.py
appenlight/lib/__init__.py
appenlight/lib/api.py
appenlight/lib/cache_regions.py
appenlight/lib/configurator.py
appenlight/lib/encryption.py
appenlight/lib/enums.py
appenlight/lib/ext_json.py
appenlight/lib/helpers.py
appenlight/lib/jinja2_filters.py
appenlight/lib/logging.py
appenlight/lib/redis_keys.py
appenlight/lib/request.py
appenlight/lib/rule.py
appenlight/lib/social.py
appenlight/lib/sqlalchemy_fields.py
appenlight/lib/utils/__init__.py
appenlight/lib/utils/airbrake.py
appenlight/lib/utils/date_utils.py
appenlight/lib/utils/sentry.py
appenlight/migrations/__init__.py
appenlight/migrations/env.py
appenlight/migrations/script.py.mako
appenlight/migrations/versions/55b6e612672f_initial_tables.py
appenlight/migrations/versions/e9fcfbdd9498_connect_resources_to_alert_channels.py
appenlight/models/__init__.py
appenlight/models/alert_channel.py
appenlight/models/alert_channel_action.py
appenlight/models/application.py
appenlight/models/application_postprocess_conf.py
appenlight/models/auth_token.py
appenlight/models/config.py
appenlight/models/event.py
appenlight/models/external_identity.py
appenlight/models/group.py
appenlight/models/group_permission.py
appenlight/models/group_resource_permission.py
appenlight/models/log.py
appenlight/models/metric.py
appenlight/models/plugin_config.py
appenlight/models/report.py
appenlight/models/report_assignment.py
appenlight/models/report_comment.py
appenlight/models/report_group.py
appenlight/models/report_stat.py
appenlight/models/resource.py
appenlight/models/slow_call.py
appenlight/models/tag.py
appenlight/models/user.py
appenlight/models/user_group.py
appenlight/models/user_permission.py
appenlight/models/user_resource_permission.py
appenlight/models/alert_channels/__init__.py
appenlight-2.0.0rc1.dist-info/METADATA
appenlight-2.0.0rc1.dist-info/WHEEL
appenlight-2.0.0rc1.dist-info/entry_points.txt
appenlight-2.0.0rc1.dist-info/top_level.txt
appenlight-2.0.0rc1.dist-info/RECORD
