Metadata-Version: 2.1
Name: appenlight
Version: 2.0.0rc1
Summary: appenlight
Home-page: http://rhodecode.com
Author: RhodeCode GmbH
License: Apache 2.0
Keywords: web wsgi bfg pylons pyramid flask django monitoring apm instrumentation appenlight
Platform: UNKNOWN
Classifier: Framework :: Pyramid
Classifier: License :: OSI Approved :: Apache Software License
Classifier: Programming Language :: Python
Classifier: Programming Language :: Python :: 3 :: Only
Classifier: Programming Language :: Python :: 3.6
Classifier: Topic :: System :: Monitoring
Classifier: Topic :: Software Development
Classifier: Topic :: Software Development :: Bug Tracking
Classifier: Topic :: Internet :: Log Analysis
Classifier: Topic :: Internet :: WWW/HTTP
Classifier: Topic :: Internet :: WWW/HTTP :: WSGI :: Application
Requires-Python: >=3.5
Requires-Dist: repoze.sendmail (==4.4.1)
Requires-Dist: pyramid (==1.10.2)
Requires-Dist: pyramid-tm (==2.2.1)
Requires-Dist: pyramid-debugtoolbar
Requires-Dist: pyramid-authstack (==1.0.1)
Requires-Dist: SQLAlchemy (==1.2.18)
Requires-Dist: alembic (==1.0.8)
Requires-Dist: webhelpers2 (==2.0)
Requires-Dist: transaction (==2.4.0)
Requires-Dist: zope.sqlalchemy (==1.1)
Requires-Dist: pyramid-mailer (==0.15.1)
Requires-Dist: redis (==3.2.1)
Requires-Dist: redlock-py (==1.0.8)
Requires-Dist: pyramid-jinja2 (==2.8)
Requires-Dist: psycopg2-binary (==2.7.7)
Requires-Dist: wtforms (==2.2.1)
Requires-Dist: celery (==4.2.1)
Requires-Dist: formencode (==1.3.1)
Requires-Dist: psutil (==5.6.1)
Requires-Dist: ziggurat-foundations (==0.8.3)
Requires-Dist: bcrypt (==3.1.6)
Requires-Dist: appenlight-client
Requires-Dist: markdown (==3.0.1)
Requires-Dist: colander (==1.7)
Requires-Dist: defusedxml (==0.5.0)
Requires-Dist: dogpile.cache (==0.7.1)
Requires-Dist: pyramid-redis-sessions (==1.0.1)
Requires-Dist: simplejson (==3.16.0)
Requires-Dist: waitress (==1.2.1)
Requires-Dist: gunicorn (==19.9.0)
Requires-Dist: uwsgi (==2.0.18)
Requires-Dist: requests (==2.21.0)
Requires-Dist: requests-oauthlib (==1.2.0)
Requires-Dist: gevent (==1.4.0)
Requires-Dist: pygments (==2.3.1)
Requires-Dist: lxml (==4.3.2)
Requires-Dist: paginate (==0.5.6)
Requires-Dist: paginate-sqlalchemy (==0.3.0)
Requires-Dist: elasticsearch (<7.0.0,>=6.0.0)
Requires-Dist: mock (==1.0.1)
Requires-Dist: itsdangerous (==1.1.0)
Requires-Dist: camplight (==0.9.6)
Requires-Dist: jira (==1.0.7)
Requires-Dist: python-dateutil (==2.5.3)
Requires-Dist: authomatic (==0.1.0.post1)
Requires-Dist: cryptography (==2.6.1)
Provides-Extra: dev
Requires-Dist: coverage ; extra == 'dev'
Requires-Dist: pytest ; extra == 'dev'
Requires-Dist: pyramid ; extra == 'dev'
Requires-Dist: tox ; extra == 'dev'
Requires-Dist: mock ; extra == 'dev'
Requires-Dist: pytest-mock ; extra == 'dev'
Requires-Dist: webtest ; extra == 'dev'
Provides-Extra: lint
Requires-Dist: black ; extra == 'lint'
